gps/__init__.py
gps/__version__.py
gps/client.py
gps/fake.py
gps/gps.py
gps/misc.py
gps/watch_options.py
gps-3.19.dist-info/AUTHORS
gps-3.19.dist-info/COPYING
gps-3.19.dist-info/METADATA
gps-3.19.dist-info/WHEEL
gps-3.19.dist-info/top_level.txt
gps-3.19.dist-info/RECORD
