Metadata-Version: 1.0
Name: gps
Version: 3.19
Summary: GPSD client
Home-page: https://gitlab.com/gpsd/gpsd
Author: Eric S. Raymond
Author-email: esr@thyrsus.com
License: BSD
Keywords: gsp
Platform: UNKNOWN
